{"doc_id": "jmir_23_P_964-2", "sent_id": "jmir_23_P_964-2", "token_ids": ["jmir_23_P_964-2:0-3", "jmir_23_P_964-2:4-13", "jmir_23_P_964-2:14-23", "jmir_23_P_964-2:24-29", "jmir_23_P_964-2:30-38", "jmir_23_P_964-2:39-40", "jmir_23_P_964-2:41-50", "jmir_23_P_964-2:51-62", "jmir_23_P_964-2:63-65", "jmir_23_P_964-2:66-77", "jmir_23_P_964-2:78-87", "jmir_23_P_964-2:88-94", "jmir_23_P_964-2:95-98", "jmir_23_P_964-2:99-102", "jmir_23_P_964-2:103-107", "jmir_23_P_964-2:108-120", "jmir_23_P_964-2:121-128", "jmir_23_P_964-2:129-132", "jmir_23_P_964-2:133-143", "jmir_23_P_964-2:144-154", "jmir_23_P_964-2:155-159", "jmir_23_P_964-2:160-167", "jmir_23_P_964-2:168-178", "jmir_23_P_964-2:179-189"], "tokens": ["The", "Push-Pull", "Mentoring", "Model", "provides", "a", "promising", "alternative", "to", "traditional", "mentoring", "models", "and", "may", "help", "institutions", "address", "the", "challenges", "associated", "with", "limited", "mentorship", "resources."], "graph": {"entities": [[0, 1, "UNK", "UNK", 1.0], [1, 4, "UNK", "UNK", 0.0], [5, 12, "UNK", "UNK", 1.0], [13, 23, "UNK", "UNK", 0.0]], "triggers": [[4, 5, "Conclusions/Implications", 1.0]], "relations": [], "roles": [[0, 0, "Agent", 1.0], [0, 1, "Agent", 0.7656628442319158], [0, 2, "PrimaryObject", 1.0], [0, 3, "Implications", 0.7656628442319158]]}}
